scripts/__init__.py
scripts/iocmite.py
suricata_misp/___init__.py
suricata_misp/last_run.py
suricata_misp/misp_client.py
suricata_misp/sched_client.py
suricata_misp/sightings.py
suricata_misp/suricata_dataset.py
utils/__init__.py
utils/logger.py
iocmite-0.1.dist-info/LICENCE.md
iocmite-0.1.dist-info/METADATA
iocmite-0.1.dist-info/WHEEL
iocmite-0.1.dist-info/entry_points.txt
iocmite-0.1.dist-info/top_level.txt
iocmite-0.1.dist-info/RECORD
