Metadata-Version: 2.1
Name: iocmite
Version: 0.1
Summary: Import indicators of different data sources to dataset Suricata and add sightings in MISP on this indicators
Home-page: https://github.com/sebdraven/IOCmite
Author: Sebastien Larinier @Sebdraven
License: Apache
Keywords: misp suricata datasets
Classifier: License :: OSI Approved :: MIT License
Classifier: Development Status :: 5 - Production/Stable
Classifier: Programming Language :: Python :: 3
Requires-Python: >=3.6
License-File: LICENCE.md
Requires-Dist: pymisp
Requires-Dist: redis
Requires-Dist: tailer
Requires-Dist: idstools
